profilescout/__about__.py
profilescout/__init__.py
profilescout/__main__.py
profilescout/classification/__init__.py
profilescout/classification/classifier.py
profilescout/cli/__init__.py
profilescout/common/__init__.py
profilescout/common/constants.py
profilescout/common/exceptions.py
profilescout/common/interfaces.py
profilescout/common/structures.py
profilescout/common/wrappers.py
profilescout/extraction/__init__.py
profilescout/extraction/htmlextract.py
profilescout/link/__init__.py
profilescout/link/utils.py
profilescout/web/__init__.py
profilescout/web/crawl.py
profilescout/web/manager.py
profilescout/web/webdriver.py
profilescout/web/webpage.py
profilescout-0.3.2.post1.dist-info/METADATA
profilescout-0.3.2.post1.dist-info/WHEEL
profilescout-0.3.2.post1.dist-info/entry_points.txt
profilescout-0.3.2.post1.dist-info/licenses/LICENSE
profilescout-0.3.2.post1.dist-info/RECORD
