Metadata-Version: 2.1
Name: profilescout
Version: 0.3.2.post1
Summary: Profile Scout is a kit that uses crawling and machine learning to identify profile pages on any website, simplifying the process of extracting user profiles, gathering information, and performing targeted actions.
Project-URL: Documentation, https://github.com/todorovicsrdjan/profilescout#readme
Project-URL: Issues, https://github.com/todorovicsrdjan/profilescout/issues
Project-URL: Source, https://github.com/todorovicsrdjan/profilescout
Author-email: TodorovicSrdjan <tsrdjan@pm.me>
License-Expression: MIT
License-File: LICENSE
Keywords: analysis,data_collection,data_extraction,detection,profile,profile_page,scraping
Classifier: Development Status :: 1 - Planning
Classifier: Intended Audience :: Developers
Classifier: Intended Audience :: Science/Research
Classifier: License :: OSI Approved :: GNU General Public License v3 or later (GPLv3+)
Classifier: Operating System :: OS Independent
Classifier: Programming Language :: Python
Classifier: Programming Language :: Python :: 3.7
Classifier: Programming Language :: Python :: 3.8
Classifier: Programming Language :: Python :: 3.9
Classifier: Programming Language :: Python :: 3.10
Classifier: Programming Language :: Python :: 3.11
Classifier: Topic :: Internet
Classifier: Topic :: Scientific/Engineering :: Image Processing
Classifier: Topic :: Scientific/Engineering :: Image Recognition
Classifier: Topic :: Scientific/Engineering :: Information Analysis
Requires-Python: >=3.7
Requires-Dist: bs4
Requires-Dist: html2text
Requires-Dist: numpy
Requires-Dist: phonenumbers
Requires-Dist: pillow
Requires-Dist: selenium
Requires-Dist: tensorflow
Requires-Dist: tldextract
